finance_calculator/__init__.py
finance_calculator/__main__.py
finance_calculator/calculator.py
finance_calculator_Novoselov_Efim-0.1.dist-info/METADATA
finance_calculator_Novoselov_Efim-0.1.dist-info/WHEEL
finance_calculator_Novoselov_Efim-0.1.dist-info/entry_points.txt
finance_calculator_Novoselov_Efim-0.1.dist-info/top_level.txt
finance_calculator_Novoselov_Efim-0.1.dist-info/RECORD
