Metadata-Version: 2.1
Name: finance-calculator-Novoselov_Efim
Version: 0.1
Summary: A package for calculating net profit and ROI
Home-page: UNKNOWN
Author: Novoselov Efim/Stanislav Kuleshov
Author-email: kuku@mail.com
License: UNKNOWN
Platform: UNKNOWN
